skeleton/__init__.py
skeleton/admin.py
skeleton/apps.py
skeleton/models.py
skeleton/tests.py
skeleton/urls.py
skeleton/views.py
skeleton/__pycache__/__init__.cpython-37.pyc
skeleton/__pycache__/admin.cpython-37.pyc
skeleton/__pycache__/models.cpython-37.pyc
skeleton/__pycache__/urls.cpython-37.pyc
skeleton/__pycache__/views.cpython-37.pyc
skeleton/migrations/__init__.py
skeleton/migrations/__pycache__/__init__.cpython-37.pyc
skeleton/static/admin/style.css
skeleton/templates/admin/base_site.html
django_skeleton-0.1.2.dist-info/LICENSE
django_skeleton-0.1.2.dist-info/METADATA
django_skeleton-0.1.2.dist-info/WHEEL
django_skeleton-0.1.2.dist-info/top_level.txt
django_skeleton-0.1.2.dist-info/RECORD
