Metadata-Version: 2.1
Name: django-skeleton
Version: 0.1.2
Summary: A template repository of Django admin features and style enhancements.
Home-page: https://www.github.com/lesliegearhart/django-skeleton
Author: Leslie Gearhart
Author-email: leslie@lesliegearhart.com
License: GNU
Platform: UNKNOWN
Classifier: Environment :: Web Environment
Classifier: Framework :: Django
Classifier: Framework :: Django :: 3.0
Classifier: Intended Audience :: Developers
Classifier: License :: OSI Approved :: GNU General Public License (GPL)
Classifier: Operating System :: OS Independent
Classifier: Programming Language :: Python
Classifier: Programming Language :: Python :: 3
Classifier: Programming Language :: Python :: 3 :: Only
Classifier: Programming Language :: Python :: 3.6
Classifier: Programming Language :: Python :: 3.7
Classifier: Programming Language :: Python :: 3.8
Classifier: Topic :: Utilities
